<?xml version="1.0" encoding="UTF-8"?>
<objects serializationModel="Studio.02.02.00">
	<object class="AudioFile" id="{22d8b4c6-d405-4fbe-8317-3148fc677304}">
		<property name="assetPath">
			<value>Dialogue/Overseer/overseer-battlelines20.wav</value>
		</property>
		<property name="frequencyInKHz">
			<value>48</value>
		</property>
		<property name="channelCount">
			<value>2</value>
		</property>
		<property name="length">
			<value>9.2729166666666671</value>
		</property>
		<relationship name="masterAssetFolder">
			<destination>{17e1d502-0063-4367-b634-76cbebc2aad7}</destination>
		</relationship>
	</object>
</objects>
