<?xml version="1.0" encoding="UTF-8"?>
<objects serializationModel="Studio.02.02.00">
	<object class="AudioFile" id="{6c900688-1de8-490d-a936-68dc5bbaa578}">
		<property name="assetPath">
			<value>Dialogue/Maria/maria-eph4.wav</value>
		</property>
		<property name="frequencyInKHz">
			<value>48</value>
		</property>
		<property name="channelCount">
			<value>2</value>
		</property>
		<property name="length">
			<value>6.0353750000000002</value>
		</property>
		<relationship name="masterAssetFolder">
			<destination>{17e1d502-0063-4367-b634-76cbebc2aad7}</destination>
		</relationship>
	</object>
</objects>
