<?xml version="1.0" encoding="UTF-8"?>
<objects serializationModel="Studio.02.02.00">
	<object class="AudioFile" id="{ebd18da0-a8d0-48ae-8ac1-c847dd30d9e4}">
		<property name="assetPath">
			<value>Dialogue/Maria/Commentary/maria-starttown.wav</value>
		</property>
		<property name="frequencyInKHz">
			<value>48</value>
		</property>
		<property name="channelCount">
			<value>2</value>
		</property>
		<property name="length">
			<value>3.8220208333333332</value>
		</property>
		<relationship name="masterAssetFolder">
			<destination>{17e1d502-0063-4367-b634-76cbebc2aad7}</destination>
		</relationship>
	</object>
</objects>
